LICENSE.txt
MANIFEST.in
README.rst
setup.py
aldryn_news/__init__.py
aldryn_news/admin.py
aldryn_news/cms_app.py
aldryn_news/cms_plugins.py
aldryn_news/cms_toolbar.py
aldryn_news/feeds.py
aldryn_news/forms.py
aldryn_news/managers.py
aldryn_news/menu.py
aldryn_news/models.py
aldryn_news/search_indexes.py
aldryn_news/urls.py
aldryn_news/utils.py
aldryn_news/views.py
aldryn_news.egg-info/PKG-INFO
aldryn_news.egg-info/SOURCES.txt
aldryn_news.egg-info/dependency_links.txt
aldryn_news.egg-info/not-zip-safe
aldryn_news.egg-info/requires.txt
aldryn_news.egg-info/top_level.txt
aldryn_news/locale/de/LC_MESSAGES/django.mo
aldryn_news/locale/de/LC_MESSAGES/django.po
aldryn_news/locale/en/LC_MESSAGES/django.mo
aldryn_news/locale/en/LC_MESSAGES/django.po
aldryn_news/locale/fr/LC_MESSAGES/django.mo
aldryn_news/locale/fr/LC_MESSAGES/django.po
aldryn_news/locale/it/LC_MESSAGES/django.mo
aldryn_news/locale/it/LC_MESSAGES/django.po
aldryn_news/migrations/0001_initial.py
aldryn_news/migrations/0002_auto__add_category__add_categorytranslation__add_unique_categorytransl.py
aldryn_news/migrations/0003_auto__add_field_news_category.py
aldryn_news/migrations/0004_auto__del_unique_newstranslation_slug__add_unique_newstranslation_slug.py
aldryn_news/migrations/0005_auto__add_tagtranslation__add_unique_tagtranslation_language_code_mast.py
aldryn_news/migrations/0006_auto__del_field_tag_slug__del_field_tag_name.py
aldryn_news/migrations/0007_auto__del_unique_tagtranslation_slug__add_unique_tagtranslation_slug_l.py
aldryn_news/migrations/0008_auto__add_field_latestnewsplugin_type_list.py
aldryn_news/migrations/0009_auto__add_newslinksplugin.py
aldryn_news/migrations/__init__.py
aldryn_news/sitemaps/__init__.py
aldryn_news/sitemaps/sitemap.py
aldryn_news/templates/aldryn_news/base.html
aldryn_news/templates/aldryn_news/news_detail.html
aldryn_news/templates/aldryn_news/news_list.html
aldryn_news/templates/aldryn_news/includes/news_items.html
aldryn_news/templates/aldryn_news/plugins/archive.html
aldryn_news/templates/aldryn_news/plugins/categories.html
aldryn_news/templates/aldryn_news/plugins/latest_entries.html
aldryn_news/templates/aldryn_news/plugins/news_links.html
